kradmin/__init__.py
kradmin/apps.py
kradmin/models.py
kradmin/urls.py
kradmin/views.py
kradmin/static/css/kradmin.css
kradmin/static/js/kradmin.js
kradmin/templates/kradmin/base.html
vadmin/__init__.py
vadmin/apps.py
vadmin/models.py
vadmin/urls.py
vadmin/views.py
vadmin/static/css/vadmin.css
vadmin/static/js/vadmin.js
vadmin/templates/vadmin/base.html
django_vadmin-0.1.0.dist-info/AUTHORS.rst
django_vadmin-0.1.0.dist-info/LICENSE
django_vadmin-0.1.0.dist-info/METADATA
django_vadmin-0.1.0.dist-info/WHEEL
django_vadmin-0.1.0.dist-info/top_level.txt
django_vadmin-0.1.0.dist-info/RECORD
