Metadata-Version: 2.1
Name: django-vadmin
Version: 0.1.0
Summary: vadmin reusable app for Django
Home-page: https://github.com/bushig/django-vadmin
Author: bushig
Author-email: azerot966@gmail.com
License: MIT
Keywords: django-vadmin
Platform: UNKNOWN
Classifier: Development Status :: 1 - Planning
Classifier: Framework :: Django :: 2.0
Classifier: Framework :: Django :: 2.1
Classifier: Framework :: Django :: 2.2
Classifier: Intended Audience :: Developers
Classifier: License :: OSI Approved :: MIT License
Classifier: Natural Language :: English
Classifier: Programming Language :: Python :: 3
Classifier: Programming Language :: Python :: 3.4
Classifier: Programming Language :: Python :: 3.5
Classifier: Programming Language :: Python :: 3.6
Classifier: Programming Language :: Python :: 3.7
Classifier: Programming Language :: Python :: 3.8
Requires-Dist: django-model-utils (>=2.0)
